google_api_v3_helper/__init__.py
google_api_v3_helper/google_api_helper.py
google_api_v3_helper-0.5.dev0.dist-info/LICENSE.txt
google_api_v3_helper-0.5.dev0.dist-info/METADATA
google_api_v3_helper-0.5.dev0.dist-info/WHEEL
google_api_v3_helper-0.5.dev0.dist-info/top_level.txt
google_api_v3_helper-0.5.dev0.dist-info/RECORD
