Metadata-Version: 2.1
Name: google-api-v3-helper
Version: 0.5.dev0
Summary: help python developper to use some of the Google Drive API v3 easily
Home-page: https://github.com/sbi-rviot/google_api_helper
Author: Renaud Viot
Author-email: renaud.viot@simply-bi.com
License: UNKNOWN
Platform: UNKNOWN
Classifier: Programming Language :: Python :: 3
Classifier: License :: OSI Approved :: MIT License
Classifier: Operating System :: OS Independent
Requires-Dist: oauth2client
Requires-Dist: google-api-python-client (==1.7.9)
Requires-Dist: google-auth-httplib2 (==0.0.3)
Requires-Dist: google-auth-oauthlib (==0.4.0)
